{"namedChunkGroups":{"polyfill":{"name":"polyfill","assets":[{"name":"webpack-runtime-cdc44520a65a62bf5593.js","size":4998},{"name":"polyfill-2fd80e6fd58c171554e2.js","size":82659}],"filteredAssets":0,"assetsSize":87657,"filteredAuxiliaryAssets":2,"auxiliaryAssetsSize":221549},"app":{"name":"app","assets":[{"name":"webpack-runtime-cdc44520a65a62bf5593.js","size":4998},{"name":"styles.f03cb196a8e238f9b05d.css","size":22390},{"name":"framework-c954e3928f59ffdad729.js","size":129760},{"name":"app-f4da7762619a78c2e1dd.js","size":69601}],"filteredAssets":0,"assetsSize":226749,"filteredAuxiliaryAssets":5,"auxiliaryAssetsSize":768679},"component---src-pages-404-tsx":{"name":"component---src-pages-404-tsx","assets":[{"name":"component---src-pages-404-tsx-ea783943f9238b665768.js","size":835}],"filteredAssets":0,"assetsSize":835,"filteredAuxiliaryAssets":1,"auxiliaryAssetsSize":1907},"component---src-pages-index-tsx":{"name":"component---src-pages-index-tsx","assets":[{"name":"styles.f03cb196a8e238f9b05d.css","size":22390},{"name":"component---src-pages-index-tsx-92c56bcf3ca5bde82786.js","size":88062}],"filteredAssets":0,"assetsSize":110452,"filteredAuxiliaryAssets":4,"auxiliaryAssetsSize":751133}},"assetsByChunkName":{"polyfill":["webpack-runtime-cdc44520a65a62bf5593.js","polyfill-2fd80e6fd58c171554e2.js"],"app":["webpack-runtime-cdc44520a65a62bf5593.js","styles.f03cb196a8e238f9b05d.css","framework-c954e3928f59ffdad729.js","app-f4da7762619a78c2e1dd.js"],"component---src-pages-404-tsx":["component---src-pages-404-tsx-ea783943f9238b665768.js"],"component---src-pages-index-tsx":["styles.f03cb196a8e238f9b05d.css","component---src-pages-index-tsx-92c56bcf3ca5bde82786.js"]},"childAssetsByChunkName":{}}